src/fp_int_acc.v
module fp_int_acc (
    input          clk,
    input          rst,
    input          start,
    input          sign_in,
    input  [4:0]   exp_min,
    input  [31:0]  fixed_point_acc,
    input  [4:0]   exp_in,
    input  [13:0]  fixed_point_in,
    output [4:0]   exp_out,
    output [31:0]  fixed_point_out,
    output reg     done
);

wire [4:0] diff;
assign diff = exp_in - exp_min;

reg [31:0] fixed_point_reg;
reg [4:0] exp_reg;
reg [31:0] fixed_point_in_shifted, fixed_point_acc_shifted;
reg shifted;

always @(posedge clk or negedge rst)
    if (!rst) begin
        fixed_point_reg <= 0;
        done <= 0;
    end
    else if (shifted&&!done) begin
        fixed_point_reg <= sign_in? fixed_point_acc_shifted - fixed_point_in_shifted: fixed_point_acc_shifted + fixed_point_in_shifted;
        shifted <= 0;
        done <= 1;
    end

always @(posedge clk or negedge rst) begin
    if (!rst) begin
        fixed_point_in_shifted <= 0;
        fixed_point_acc_shifted <= 0;
        exp_reg <= 0;
        shifted <= 0;
    end
    else if (start && !shifted) begin
        done <= 0;
        if (~|diff) begin
            exp_reg <= exp_min;
            fixed_point_in_shifted <= fixed_point_in;
            fixed_point_acc_shifted <= fixed_point_acc;
        end
        else if (!diff[4]) begin // If exp_min < exp_in, diff[4] would be 0
            exp_reg <= exp_min;
            fixed_point_in_shifted <= fixed_point_in<<diff; //shift by the two's complement of diff since diff would be negative values here
            fixed_point_acc_shifted <= fixed_point_acc;
        end
        else begin // If exp_min > exp_in, diff[4] would be 1
            exp_reg <= exp_in;
            fixed_point_in_shifted <= fixed_point_in;
            fixed_point_acc_shifted <= fixed_point_acc<<-diff; //shift by diff
        end
        shifted <= 1;
    end
    else begin
        fixed_point_in_shifted <= fixed_point_in;
        fixed_point_acc_shifted <= fixed_point_acc;
    end
end

assign fixed_point_out = fixed_point_reg;
assign exp_out = exp_reg;

endmodule

src/fp_int_mul_bit_serial.v
  // To get started fp_int_mul unit here is only for fixed-precision arithmetic: fp16 x+ int4 operations
// fp16 : 1=bit sign + 5-bit exponent + 10-bit mantissa
module fp_int_mul_bit_serial #(
    parameter ACT_WIDTH = 16,
    // parameter W_WIDTH  = 4,
    parameter ACC_WIDTH = 32
)(
    input                  clk,
    input                  rst,
    input [ACT_WIDTH-1:0]  act,
    input                  w,
    input                  valid,
    input                  set, 
    input [3:0]            precision,
    // output [ACC_WIDTH-1:0] result,
    output reg             sign_out,
    output reg [4:0]       exp_out,
    output [13:0]          mantissa_out,
    output reg             start_acc    
);

// reg [ACT_WIDTH-1:0]       _act;
// reg                       _w;
wire                      act_sign;
wire [4:0]                act_exponent;
wire [9:0]                act_mantissa;
wire [10:0]               fixed_mantissa;
assign {act_sign, act_exponent, act_mantissa} = act;
assign fixed_mantissa = {1'b1, act_mantissa};

reg [3:0]             _precision;

always @(posedge clk or negedge rst)
    if (!rst) _precision <= 0;
    else if (set) _precision <= precision;

reg [2:0]             count;

always @(posedge clk or negedge rst) begin
    if (!rst) begin
        count <= 0;
        // start_acc <= 0;
        // _act <= 0;
        // _w <= 0;
    end
    else begin
        if (valid) begin
            // _act <= act;
            // _w <= w;
            if (count<_precision-1) count <= count + 1;
            else begin
                count <= 0;
                // start_acc <= 1;
            end
        end
        else begin
            // _act <= _act;
            count <= 0;
        end
    end
end

// The accumulator in the Multiplier unit
reg  [13:0] mantissa_reg;
// wire  [14:0] mantissa_temp;
reg   [13:0] shifted_fp;

fixed_point_adder fixed_adder(mantissa_reg, shifted_fp, mantissa_out);

always @(posedge clk or negedge rst)
    if (!rst) mantissa_reg <= 0;
    else if (!start_acc) mantissa_reg <= mantissa_out;
    else mantissa_reg<=0;


always @(*) begin
    case (count)
        3'b000: begin
            shifted_fp = 14'b0;
            // start_acc = 0;
        end
        3'b001: shifted_fp = w? fixed_mantissa<<2: 14'b0;
        3'b010: shifted_fp = w? fixed_mantissa<<1: 14'b0;
        3'b011: begin
            shifted_fp = w? fixed_mantissa: 14'b0;
            // start_acc = 1;
        end
        default: begin
            shifted_fp = 14'b0;
            // sign_out = 0;
            // start_acc = 0;
        end
    endcase
end

always @(posedge clk or negedge rst)
    if (!rst) begin
        start_acc <= 0;
        sign_out <= 0;
        exp_out <= 0;
    end
    else if (count == 0) begin
        exp_out <= act_exponent;
        sign_out <= w^act[ACT_WIDTH-1];
        start_acc <= 0;
    end
    else if (count==_precision-1) start_acc <= 1;
    else start_acc <= 0;

endmodule

module fixed_point_adder(
    input      [13:0]  A,
    input      [13:0]  B,
    output     [13:0]  C
);
// This is the intermediate represetation in order to have the least # of rounding at the end of computation.
// The 14-bit fixed point representation consists of 4 bits . 10 bits mantissa
// which is able to hold everything accurately without 
assign C = A + B;
endmodule

src/fp_int_mac_bit_serial.v
module fp_int_mac_bit_serial #(
    parameter ACT_WIDTH = 16,
    parameter ACC_WIDTH = 32
)(
    input                   clk,
    input                   rst,
    input                   valid,
    input [3:0]             precision,
    input                   set,
    input [ACT_WIDTH-1:0]   act,
    input                   w,
    input [4:0]             exp_min,
    input [31:0]            fixed_point_acc,
    output [4:0]            exp_out,
    output [ACC_WIDTH-1:0]  fixed_point_out,
    output                  done
);

// Intermediate signals between Multiplier and Accumulator
wire                    start_acc;
wire                    sign_out;
wire [4:0]              exp_out_mul;
wire [13:0]             mantissa_out;

// Instantiate the Multiplier Unit (fp16 × int4)
fp_int_mul_bit_serial #(
    .ACT_WIDTH(ACT_WIDTH)
) mul_unit (
    .clk(clk),
    .rst(rst),
    .act(act),
    .w(w),
    .valid(valid),
    .set(set),
    .precision(precision),
    .sign_out(sign_out),
    .exp_out(exp_out_mul),
    .mantissa_out(mantissa_out),
    .start_acc(start_acc)
);

// Instantiate the Accumulator Unit
fp_int_acc acc_unit (
    .clk(clk),
    .rst(rst),
    .start(start_acc),
    .sign_in(sign_out),
    .exp_min(exp_min),
    .fixed_point_acc(fixed_point_acc),
    .exp_in(exp_out_mul),
    .fixed_point_in(mantissa_out),
    .exp_out(exp_out),
    .fixed_point_out(fixed_point_out),
    .done(done)
);

endmodule

tb/fp_int_mac_bit_serial_tb.v
module fp_int_mac_bit_serial_tb;

    // Parameters
    parameter ACT_WIDTH = 16;
    parameter ACC_WIDTH = 32;

    // Testbench signals
    reg clk;
    reg rst;
    reg valid;
    reg [3:0] precision;
    reg set;
    reg [ACT_WIDTH-1:0] act;
    reg w;
    reg [4:0] exp_min;
    reg [31:0] fixed_point_acc;
    wire [4:0] exp_out;
    wire [ACC_WIDTH-1:0] fixed_point_out;
    wire done;

    // Instantiate the MAC unit
    fp_int_mac_bit_serial #(
        .ACT_WIDTH(ACT_WIDTH),
        .ACC_WIDTH(ACC_WIDTH)
    ) uut (
        .clk(clk),
        .rst(rst),
        .valid(valid),
        .precision(precision),
        .set(set),
        .act(act),
        .w(w),
        .exp_min(exp_min),
        .fixed_point_acc(fixed_point_acc),
        .exp_out(exp_out),
        .fixed_point_out(fixed_point_out),
        .done(done)
    );

    // Clock generation
    always #5 clk = ~clk; // Toggle clock every 5 time units

    // Test stimulus
    initial begin
        // Initialize signals
        clk = 0;
        rst = 1;
        valid = 0;
        precision = 4;
        set = 0;
        act = 16'b0100010101101001; // Example FP16 value
        w = 0;
        exp_min = 5'b10000; // Example exponent min
        fixed_point_acc = 32'b00000000000000000000000000000010; // Start accumulator at 0

        // Create VCD file for GTKWave
        $dumpfile("fp_int_mac_bit_serial.vcd");
        $dumpvars(0, fp_int_mac_bit_serial_tb);
            
        // Apply reset
        #10 rst = 0;
        #10 rst = 1;

        #10 set = 1;
        #10 set = 0;

        // Start the first MAC operation
        #15 valid = 1;
        repeat (10) begin
            #10 w = ~w;
        end
        #10 valid = 0;

        #80

        // Start another MAC operation with different values
        act = 16'b0100101010101010; // Different FP16 value
        w = 1;
        valid = 1;
        #10 w = ~w;
        #10 w = ~w;
        #10 w = ~w;
        #5 act = 16'b1011111010000000; // Different FP16 value
        #5 w = ~w;
        #5 w = 1;
        valid = 1;
        repeat (4) begin
            #10 w = ~w;
        end

        #10 valid = 0;
        #10 valid = 1;
        w = 0;
        #80

        // End simulation
        $finish;
    end

endmodule

fp_int_mac_bit_serial.vcd
$date
	Mon Feb 24 22:33:53 2025
$end
$version
	Icarus Verilog
$end
$timescale
	1s
$end
$scope module fp_int_mac_bit_serial_tb $end
$var wire 32 ! fixed_point_out [31:0] $end
$var wire 5 " exp_out [4:0] $end
$var wire 1 # done $end
$var reg 16 $ act [15:0] $end
$var reg 1 % clk $end
$var reg 5 & exp_min [4:0] $end
$var reg 32 ' fixed_point_acc [31:0] $end
$var reg 4 ( precision [3:0] $end
$var reg 1 ) rst $end
$var reg 1 * set $end
$var reg 1 + valid $end
$var reg 1 , w $end
$scope module uut $end
$var wire 16 - act [15:0] $end
$var wire 1 % clk $end
$var wire 5 . exp_min [4:0] $end
$var wire 32 / fixed_point_acc [31:0] $end
$var wire 4 0 precision [3:0] $end
$var wire 1 ) rst $end
$var wire 1 * set $end
$var wire 1 + valid $end
$var wire 1 , w $end
$var wire 1 1 start_acc $end
$var wire 1 2 sign_out $end
$var wire 14 3 mantissa_out [13:0] $end
$var wire 32 4 fixed_point_out [31:0] $end
$var wire 5 5 exp_out_mul [4:0] $end
$var wire 5 6 exp_out [4:0] $end
$var wire 1 # done $end
$scope module acc_unit $end
$var wire 1 % clk $end
$var wire 5 7 exp_min [4:0] $end
$var wire 5 8 exp_out [4:0] $end
$var wire 32 9 fixed_point_acc [31:0] $end
$var wire 32 : fixed_point_out [31:0] $end
$var wire 1 ) rst $end
$var wire 1 1 start $end
$var wire 1 2 sign_in $end
$var wire 14 ; fixed_point_in [13:0] $end
$var wire 5 < exp_in [4:0] $end
$var wire 5 = diff [4:0] $end
$var reg 1 # done $end
$var reg 5 > exp_reg [4:0] $end
$var reg 32 ? fixed_point_acc_shifted [31:0] $end
$var reg 32 @ fixed_point_in_shifted [31:0] $end
$var reg 32 A fixed_point_reg [31:0] $end
$var reg 1 B shifted $end
$upscope $end
$scope module mul_unit $end
$var wire 16 C act [15:0] $end
$var wire 1 % clk $end
$var wire 5 D exp_out [4:0] $end
$var wire 4 E precision [3:0] $end
$var wire 1 ) rst $end
$var wire 1 * set $end
$var wire 1 + valid $end
$var wire 1 , w $end
$var wire 14 F mantissa_out [13:0] $end
$var wire 11 G fixed_mantissa [10:0] $end
$var wire 1 H act_sign $end
$var wire 10 I act_mantissa [9:0] $end
$var wire 5 J act_exponent [4:0] $end
$var reg 4 K _precision [3:0] $end
$var reg 3 L count [2:0] $end
$var reg 14 M mantissa_reg [13:0] $end
$var reg 14 N shifted_fp [13:0] $end
$var reg 1 2 sign_out $end
$var reg 1 1 start_acc $end
$scope module fixed_adder $end
$var wire 14 O A [13:0] $end
$var wire 14 P B [13:0] $end
$var wire 14 Q C [13:0] $end
$upscope $end
$upscope $end
$upscope $end
$upscope $end
$enddefinitions $end
#0
$dumpvars
bx Q
b0 P
bx O
b0 N
bx M
bx L
bx K
b10001 J
b101101001 I
0H
b10101101001 G
bx F
b100 E
b10001 D
b100010101101001 C
xB
bx A
bx @
bx ?
bx >
b1 =
b10001 <
bx ;
bx :
b10 9
bx 8
b10000 7
bx 6
b10001 5
bx 4
bx 3
02
x1
b100 0
b10 /
b10000 .
b100010101101001 -
0,
0+
0*
1)
b100 (
b10 '
b10000 &
0%
b100010101101001 $
x#
bx "
bx !
$end
#5
b0 L
b0 3
b0 ;
b0 F
b0 Q
b0 M
b0 O
01
b10 ?
b0xxxxxxxxxxxxxx @
1%
#10
0B
b0 "
b0 6
b0 8
b0 >
b0 ?
b0 @
0#
b0 !
b0 4
b0 :
b0 A
b0 K
0%
0)
#15
1%
#20
0%
1)
#25
b10 ?
1%
#30
0%
1*
#35
b100 K
1%
#40
0%
0*
#45
1%
#50
0%
#55
b1 L
1%
1+
#60
0%
#65
b1010110100100 @
b1010110100100 M
b1010110100100 O
b10 L
b10000001110110 3
b10000001110110 ;
b10000001110110 F
b10000001110110 Q
b101011010010 N
b101011010010 P
1%
1,
#70
0%
#75
b11 L
b1010110100100 3
b1010110100100 ;
b1010110100100 F
b1010110100100 Q
b0 N
b0 P
1%
0,
#80
0%
#85
12
b1101100001101 @
11
b1101100001101 M
b1101100001101 O
b0 L
b1101100001101 3
b1101100001101 ;
b1101100001101 F
b1101100001101 Q
b0 N
b0 P
1%
1,
#90
0%
#95
b1 L
b0 3
b0 ;
b0 F
b0 Q
b0 M
b0 O
01
1B
b11011000011010 @
b10000 "
b10000 6
b10000 8
b10000 >
02
1%
0,
#100
0%
#105
b1010110100100 @
1#
0B
b11011000011100 !
b11011000011100 4
b11011000011100 :
b11011000011100 A
b1010110100100 M
b1010110100100 O
b10 L
b10000001110110 3
b10000001110110 ;
b10000001110110 F
b10000001110110 Q
b101011010010 N
b101011010010 P
1%
1,
#110
0%
#115
b11 L
b1010110100100 3
b1010110100100 ;
b1010110100100 F
b1010110100100 Q
b0 N
b0 P
1%
0,
#120
0%
#125
12
b1101100001101 @
11
b1101100001101 M
b1101100001101 O
b0 L
b1101100001101 3
b1101100001101 ;
b1101100001101 F
b1101100001101 Q
b0 N
b0 P
1%
1,
#130
0%
#135
b1 L
b0 3
b0 ;
b0 F
b0 Q
b0 M
b0 O
01
1B
b11011000011010 @
0#
02
1%
0,
#140
0%
#145
b1010110100100 @
1#
0B
b1010110100100 M
b1010110100100 O
b10 L
b10000001110110 3
b10000001110110 ;
b10000001110110 F
b10000001110110 Q
b101011010010 N
b101011010010 P
1%
1,
#150
0%
#155
b11 L
b1010110100100 3
b1010110100100 ;
b1010110100100 F
b1010110100100 Q
b0 N
b0 P
1%
0,
#160
0%
#165
11
b0 L
1%
0+
#170
0%
#175
b0 3
b0 ;
b0 F
b0 Q
b0 M
b0 O
01
1B
b10101101001000 @
0#
1%
#180
0%
#185
b0 @
1#
0B
b10101101001010 !
b10101101001010 4
b10101101001010 :
b10101101001010 A
1%
#190
0%
#195
1%
#200
0%
#205
1%
#210
0%
#215
1%
#220
0%
#225
1%
#230
0%
#235
1%
#240
0%
#245
b1101010101000 3
b1101010101000 ;
b1101010101000 F
b1101010101000 Q
b1101010101000 N
b1101010101000 P
b1 L
b10 =
b10010 5
b10010 <
b10010 D
b10010 J
b11010101010 G
b1010101010 I
12
1%
1+
1,
b100101010101010 $
b100101010101010 -
b100101010101010 C
#250
0%
#255
b10 L
b0 3
b0 ;
b0 F
b0 Q
b0 N
b0 P
1%
0,
#260
0%
#265
b110101010100 @
b110101010100 M
b110101010100 O
b11 L
b1001111111110 3
b1001111111110 ;
b1001111111110 F
b1001111111110 Q
b11010101010 N
b11010101010 P
1%
1,
#270
0%
#275
02
b0 L
11
b110101010100 3
b110101010100 ;
b110101010100 F
b110101010100 Q
b0 N
b0 P
1%
0,
#280
1H
b11111 =
b1111 5
b1111 <
b1111 D
b1111 J
b11010000000 G
b1010000000 I
12
0%
b1011111010000000 $
b1011111010000000 -
b1011111010000000 C
#285
b1101000000000 N
b1101000000000 P
1B
b100 ?
b1111 "
b1111 6
b1111 8
b1111 >
0#
01
b1101000000000 3
b1101000000000 ;
b1101000000000 F
b1101000000000 Q
b0 M
b0 O
b1 L
02
1%
1,
#290
0%
#295
b110100000000 N
b110100000000 P
b10 L
b10011100000000 3
b10011100000000 ;
b10011100000000 F
b10011100000000 Q
b1101000000000 M
b1101000000000 O
1#
0B
b110101011000 !
b110101011000 4
b110101011000 :
b110101011000 A
b10 ?
b1101000000000 @
1%
#300
b1101000000000 3
b1101000000000 ;
b1101000000000 F
b1101000000000 Q
b0 N
b0 P
0%
0,
#305
b11 L
1%
#310
b10000010000000 3
b10000010000000 ;
b10000010000000 F
b10000010000000 Q
b11010000000 N
b11010000000 P
0%
1,
#315
b0 N
b0 P
b0 L
b10000010000000 3
b10000010000000 ;
b10000010000000 F
b10000010000000 Q
b10000010000000 M
b10000010000000 O
11
b10000010000000 @
1%
#320
12
0%
0,
#325
1B
b100 ?
0#
01
b0 3
b0 ;
b0 F
b0 Q
b0 M
b0 O
b1 L
1%
#330
b1101000000000 3
b1101000000000 ;
b1101000000000 F
b1101000000000 Q
b1101000000000 N
b1101000000000 P
0%
1,
#335
b110100000000 N
b110100000000 P
b10 L
b10011100000000 3
b10011100000000 ;
b10011100000000 F
b10011100000000 Q
b1101000000000 M
b1101000000000 O
1#
0B
b11111111111111111101111110000100 !
b11111111111111111101111110000100 4
b11111111111111111101111110000100 :
b11111111111111111101111110000100 A
b10 ?
b1101000000000 @
1%
#340
0%
0+
#345
02
b0 N
b0 P
b10011100000000 @
b10011100000000 3
b10011100000000 ;
b10011100000000 F
b10011100000000 Q
b10011100000000 M
b10011100000000 O
b0 L
1%
#350
12
0%
0,
1+
#355
b1 L
1%
#360
0%
#365
b10 L
1%
#370
0%
#375
b11 L
1%
#380
0%
#385
11
b0 L
1%
#390
0%
#395
b1 L
b0 3
b0 ;
b0 F
b0 Q
b0 M
b0 O
01
1B
b100 ?
0#
1%
#400
0%
#405
b10 ?
b0 @
1#
0B
b11111111111111111101100100000100 !
b11111111111111111101100100000100 4
b11111111111111111101100100000100 :
b11111111111111111101100100000100 A
b10 L
1%
#410
0%
#415
b11 L
1%
#420
0%
#425
11
b0 L
1%
